cashiersync/__init__.py
cashiersync/app.py
cashiersync/config.py
cashiersync/executor.py
cashiersync/git.py
cashiersync/json_helper.py
cashiersync/ledger_exec.py
cashiersync/ledger_output_parser.py
cashiersync/lots_parser.py
cashiersync/main.py
cashiersync/model.py
cashiersync/sec_details.py
cashiersync/transactions.py
cashiersync-3.0.5.dist-info/LICENSE
cashiersync-3.0.5.dist-info/METADATA
cashiersync-3.0.5.dist-info/WHEEL
cashiersync-3.0.5.dist-info/entry_points.txt
cashiersync-3.0.5.dist-info/top_level.txt
cashiersync-3.0.5.dist-info/RECORD
