Metadata-Version: 2.1
Name: cashiersync
Version: 3.0.5
Summary: Server-side synchronization component for Cashier
Home-page: https://gitlab.com/alensiljak/cashier-sync
Author: Alen Siljak
Author-email: cashier@alensiljak.eu.org
License: UNKNOWN
Project-URL: Source Code, https://gitlab.com/alensiljak/cashier-sync.git
Keywords: cashier,finance,portfolio,ledger
Platform: UNKNOWN
Classifier: Programming Language :: Python
Classifier: Programming Language :: Python :: 3
Classifier: Development Status :: 4 - Beta
Classifier: Environment :: Other Environment
Classifier: Intended Audience :: Developers
Classifier: License :: OSI Approved :: GNU Library or Lesser General Public License (LGPL)
Classifier: Operating System :: OS Independent
Classifier: Topic :: Software Development :: Libraries :: Python Modules
License-File: LICENSE
Requires-Dist: fastapi
Requires-Dist: pyyaml
Requires-Dist: pyxdg
Requires-Dist: uvicorn
